flashlight/__init__.py
flashlight/flashlight.py
flashlight/tests.py
flashlight_pavel_ivanov928-1.0.dist-info/METADATA
flashlight_pavel_ivanov928-1.0.dist-info/WHEEL
flashlight_pavel_ivanov928-1.0.dist-info/top_level.txt
flashlight_pavel_ivanov928-1.0.dist-info/RECORD
