Metadata-Version: 2.1
Name: flashlight-pavel-ivanov928
Version: 1.0
Summary: This is a package with interview test.
Home-page: https://github.com/Splinter928/flashlight
Author: Pavel Ivanov
Author-email: pavel@ivanov928.ru
Classifier: Programming Language :: Python :: 3
Classifier: License :: OSI Approved :: MIT License
Classifier: Operating System :: OS Independent
Requires-Python: >=3.10
